epub_optimizer/__init__.py
epub_optimizer/cli.py
epub_optimizer-0.6.0.dist-info/LICENSE
epub_optimizer-0.6.0.dist-info/METADATA
epub_optimizer-0.6.0.dist-info/WHEEL
epub_optimizer-0.6.0.dist-info/entry_points.txt
epub_optimizer-0.6.0.dist-info/RECORD
