Metadata-Version: 2.3
Name: epub-optimizer
Version: 0.6.0
Summary: Optimize epub file size
License: MIT
Author: Balthazar Rouberol
Author-email: br@imap.cc
Requires-Python: >=3.9
Classifier: License :: OSI Approved :: MIT License
Classifier: Programming Language :: Python :: 3
Classifier: Programming Language :: Python :: 3.9
Classifier: Programming Language :: Python :: 3.10
Classifier: Programming Language :: Python :: 3.11
Classifier: Programming Language :: Python :: 3.12
Classifier: Programming Language :: Python :: 3.13
Requires-Dist: pillow (>=11.2.1,<12.0.0)
